nalogapi.py
nalogapi-0.1.0.dist-info/WHEEL
nalogapi-0.1.0.dist-info/METADATA
nalogapi-0.1.0.dist-info/RECORD
