Metadata-Version: 2.1
Name: nalogapi
Version: 0.1.0
Summary: Unofficial synchronous wrapper for lknpd.nalog.ru API written in Python
License: MIT
Author: Mike Ovchinnikov
Author-email: mixao@yandex.ru
Requires-Python: >=3.7,<4.0
Classifier: License :: OSI Approved :: MIT License
Classifier: Programming Language :: Python :: 3
Classifier: Programming Language :: Python :: 3.7
Classifier: Programming Language :: Python :: 3.8
Classifier: Programming Language :: Python :: 3.9
Classifier: Programming Language :: Python :: 3.10
Classifier: Programming Language :: Python :: 3.11
Requires-Dist: requests (>=2.28.1,<3.0.0)
